README.md
setup.py
redart/__init__.py
redart/__main__.py
redart.egg-info/PKG-INFO
redart.egg-info/SOURCES.txt
redart.egg-info/dependency_links.txt
redart.egg-info/entry_points.txt
redart.egg-info/requires.txt
redart.egg-info/top_level.txt