Metadata-Version: 1.0
Name: redart
Version: 0.1.3
Summary: A Redmine Artifact manager
Home-page: UNKNOWN
Author: René Groß
Author-email: rg@create.at
License: GNU GENERAL PUBLIC LICENSE v3
Platform: UNKNOWN
